localvolts_api/__init__.py
localvolts_api/auth.py
localvolts_api/customer_api.py
localvolts_api/market_api.py
localvolts_api_wrapper-0.1.dist-info/LICENSE
localvolts_api_wrapper-0.1.dist-info/METADATA
localvolts_api_wrapper-0.1.dist-info/WHEEL
localvolts_api_wrapper-0.1.dist-info/top_level.txt
localvolts_api_wrapper-0.1.dist-info/RECORD
