Metadata-Version: 2.1
Name: localvolts-api-wrapper
Version: 0.1
Summary: A Python wrapper for the LocalVolts API
Home-page: https://github.com/iconnor/localvolts
Author: Ian Connor
Author-email: ian@blissai.com
License: UNKNOWN
Platform: UNKNOWN
Classifier: Programming Language :: Python :: 3
Classifier: License :: OSI Approved :: MIT License
Classifier: Operating System :: OS Independent
Requires-Python: >=3.7
License-File: LICENSE
Requires-Dist: requests
